loadmeta/__init__.py
loadmeta/gui_inputs.py
loadmeta/metadata_parser.c
loadmeta/metadata_parser.cp39-win_amd64.pyd
loadmeta-0.1.0.dist-info/METADATA
loadmeta-0.1.0.dist-info/WHEEL
loadmeta-0.1.0.dist-info/top_level.txt
loadmeta-0.1.0.dist-info/RECORD
